{
  "skills": {
    "core_marketing": {
      "label": "Digital Marketing & Strategy",
      "keywords": [
        "Digital Marketing Strategy",
        "SEO",
        "Content Marketing",
        "Social Media Strategy",
        "Brand Strategy",
        "Lead Generation",
        "Inbound Marketing",
        "Campaign Planning",
        "B2B Marketing",
        "Audience Development",
        "Conversion Optimisation",
        "Growth Strategy",
        "Data-Driven Marketing"
      ]
    },

    "communications_pr": {
      "label": "Communications & Public Relations",
      "keywords": [
        "Strategic Communications",
        "Science Communication",
        "Technical Writing",
        "Public Relations",
        "Media Relations",
        "Editorial Planning",
        "Press Release Writing",
        "Stakeholder Engagement",
        "Corporate Communications",
        "Event Communications",
        "Webinar Production",
        "Narrative Development"
      ]
    },

    "space_industry": {
      "label": "Space Sector Expertise",
      "keywords": [
        "Space Industry Communications",
        "Earth Observation",
        "Satellite Applications",
        "Space Policy Awareness",
        "ESA Business Applications",
        "Copernicus Programme",
        "Space Outreach",
        "Astronomy Communication",
        "Scientific Research Communication",
        "Space Innovation Ecosystems",
        "Climate Services from Space",
        "Space Entrepreneurship"
      ]
    },

    "technical_skills": {
      "label": "Technical & Development Skills",
      "keywords": [
        "Python",
        "JavaScript",
        "Node.js",
        "React",
        "HTML5",
        "CSS3",
        "C",
        "C++",
        "Fortran",
        "MATLAB",
        "Linux",
        "macOS",
        "UNIX Systems",
        "Git",
        "API Integration",
        "REST APIs",
        "Data Analysis",
        "GIS (QGIS, ArcGIS)",
        "LaTeX"
      ]
    },

    "data_analytics": {
      "label": "Data & Analytics",
      "keywords": [
        "Google Analytics 4 (GA4)",
        "Matomo Analytics",
        "Data Visualisation",
        "Performance Analytics",
        "Marketing Analytics",
        "KPI Tracking",
        "User Behaviour Analysis",
        "A/B Testing",
        "Dashboard Reporting",
        "SEO Analytics",
        "Campaign Measurement"
      ]
    },

    "tools_platforms": {
      "label": "Tools & Platforms",
      "keywords": [
        "WordPress",
        "Drupal",
        "Hootsuite",
        "Asana",
        "Trello",
        "Jira",
        "Notion",
        "Slack",
        "Adobe Creative Suite",
        "Affinity Suite",
        "Figma",
        "Canva",
        "Final Cut Pro",
        "Microsoft Office 365"
      ]
    },

    "project_management": {
      "label": "Project & Programme Management",
      "keywords": [
        "Project Management",
        "Agile Methodologies",
        "Stakeholder Management",
        "Cross-functional Teams",
        "Workflow Optimisation",
        "Risk Management",
        "Sprint Planning",
        "Roadmapping",
        "OKR Planning",
        "Resource Allocation"
      ]
    },

    "leadership": {
      "label": "Leadership & Strategy",
      "keywords": [
        "Team Leadership",
        "Strategic Leadership",
        "Founder & Director Experience",
        "Organisational Development",
        "Change Management",
        "Partnership Development",
        "Mentoring",
        "Public Speaking",
        "Workshop Facilitation",
        "Community Building"
      ]
    },

    "sustainability": {
      "label": "Sustainability & ESG",
      "keywords": [
        "Sustainable Marketing",
        "ESG Strategy",
        "Net Zero Communication",
        "Climate Tech Communication",
        "Circular Economy",
        "Responsible Innovation",
        "Environmental Communication",
        "Sustainability Reporting",
        "Green Digital Skills",
        "Climate Advocacy"
      ]
    },

    "research_academic": {
      "label": "Research & Academic Skills",
      "keywords": [
        "Scientific Research",
        "Data Interpretation",
        "Astrophysics",
        "Cometary Science",
        "Academic Publishing",
        "Peer-reviewed Research",
        "Observational Astronomy",
        "Literature Review",
        "Scientific Collaboration",
        "Grant-supported Research"
      ]
    },

    "soft_skills": {
      "label": "Professional Skills",
      "keywords": [
        "Communication",
        "Problem Solving",
        "Critical Thinking",
        "Creativity",
        "Adaptability",
        "Collaboration",
        "Time Management",
        "Attention to Detail",
        "Analytical Thinking",
        "Stakeholder Communication"
      ]
    }
  }
}